LICENSE
MANIFEST.in
README
distribute_setup.py
setup.cfg
setup.py
sphinxcontrib/__init__.py
sphinxcontrib/bitbucket.py
sphinxcontrib_bitbucket.egg-info/PKG-INFO
sphinxcontrib_bitbucket.egg-info/SOURCES.txt
sphinxcontrib_bitbucket.egg-info/dependency_links.txt
sphinxcontrib_bitbucket.egg-info/namespace_packages.txt
sphinxcontrib_bitbucket.egg-info/not-zip-safe
sphinxcontrib_bitbucket.egg-info/requires.txt
sphinxcontrib_bitbucket.egg-info/top_level.txt