Metadata-Version: 1.0
Name: sphinxcontrib-bitbucket
Version: 1.0
Summary: Sphinx/BitBucket integration
Home-page: http://www.doughellmann.com/projects/sphinxcontrib-bitbucket/
Author: Doug Hellmann
Author-email: doug.hellmann@gmail.com
License: BSD
Platform: any
Classifier: Development Status :: 5 - Production/Stable
Classifier: Environment :: Console
Classifier: Intended Audience :: Developers
Classifier: License :: OSI Approved :: BSD License
Classifier: Operating System :: OS Independent
Classifier: Programming Language :: Python
Classifier: Topic :: Documentation
Classifier: Topic :: Utilities
